pytwincatparser/BaseStrategy.py
pytwincatparser/Loader.py
pytwincatparser/Twincat4024Strategy.py
pytwincatparser/TwincatDataclasses.py
pytwincatparser/__init__.py
pytwincatparser/parse_declaration.py
pytwincatparser/TwincatObjects/__init__.py
pytwincatparser/TwincatObjects/tc_plc_object.py
pytwincatparser/TwincatObjects/tc_plc_project.py
pytwincatparser/TwincatObjects/tc_solution.py
pytwincatparser/TwincatObjects/tc_twincat_project.py
pytwincatparser-0.5.5.dist-info/METADATA
pytwincatparser-0.5.5.dist-info/WHEEL
pytwincatparser-0.5.5.dist-info/licenses/LICENSE
pytwincatparser-0.5.5.dist-info/RECORD
