Metadata-Version: 2.4
Name: pytwincatparser
Version: 0.5.5
Summary: TwinCAT PLC file parser using xsdata
Project-URL: Documentation, https://github.com/drehstromer/pytwincatparser#readme
Project-URL: Issues, https://github.com/drehstromer/pytwincatparser/issues
Project-URL: Source, https://github.com/drehstromer/pytwincatparser
Author-email: drehstromer <privat@samuelruckli.ch>
License: MIT
License-File: LICENSE
Requires-Python: >=3.11
Requires-Dist: lxml>=5.3.0
Requires-Dist: pytest>=8.3.5
Requires-Dist: xsdata[lxml]>=24.12
